<?xml version="1.0" ?>
<State openmmVersion="7.0" time="0" type="State" version="1">
	<PeriodicBoxVectors>
		<A x="2" y="0" z="0"/>
		<B x="0" y="2" z="0"/>
		<C x="0" y="0" z="2"/>
	</PeriodicBoxVectors>
	<Positions>
		<Position x=".1880702511353062" y=".12400457109545943" z=".06748638577347944"/>
		<Position x=".1965883818384171" y=".21988568217378449" z=".016346840603555374"/>
		<Position x=".12792982415000126" y=".29156102715761373" z=".06139843838121324"/>
		<Position x=".1721835908502135" y=".20750506821432546" z="-.0891620483871881"/>
		<Position x=".3378287998373022" y=".2716985136519713" z=".028904767613197532"/>
		<Position x=".42299759384826513" y=".20617653462820681" z=".08867053432593577"/>
		<Position x=".36221611254582625" y=".3896602291700461" z="-.027492438022353963"/>
		<Position x=".28550286914710626" y=".4363763053368345" z="-.07368428353050549"/>
		<Position x=".4916116376504369" y=".4593128997620354" z="-.025701338050887333"/>
		<Position x=".5480528924672062" y=".4273694800255915" z=".06190575627464023"/>
		<Position x=".5712772554588961" y=".42006771771247303" z="-.1509395822639222"/>
		<Position x=".584294217735243" y=".3118636594398757" z="-.15279453096198217"/>
		<Position x=".5146223923940401" y=".4487277029879338" z="-.23953886246516243"/>
		<Position x=".7096599507131717" y=".4864190832692159" z="-.15447061995329928"/>
		<Position x=".7963897619642358" y=".46083739682125374" z="-.05119002794799132"/>
		<Position x=".7397432526872495" y=".5676196118065862" z="-.26089665845299564"/>
		<Position x=".8278684462383058" y=".6053983199914537" z="-.25613034939313567"/>
		<Position x=".47416662906379226" y=".6123764824580299" z="-.017258307550038134"/>
		<Position x=".3790798845836086" y=".6684866168818308" z="-.07282572609323158"/>
		<Position x=".6676534248311256" y=".5745213611206228" z="-.3239158592020993"/>
		<Position x=".8807564998844891" y=".5056779142480228" z="-.060548451960274786"/>
		<Position x=".7593327870339319" y=".40181751357858203" z=".014835959612684885"/>
		<Position x=".5669716540927005" y=".680438795062455" z=".051180117882115767"/>
		<Position x=".6427788817732663" y=".6280343889779564" z=".09250859383999517"/>
		<Position x=".5672642128174445" y=".8255017901904546" z=".06901186628154166"/>
		<Position x=".4720386039504302" y=".8583948025124359" z=".1106187696649594"/>
		<Position x=".6473619039137555" y=".8545881335531917" z=".13697763277866656"/>
		<Position x=".5826814594756684" y=".8747808798474429" z="-.02698230480311752"/>
	</Positions>
</State>
